mock_alchemy/__init__.py
mock_alchemy/comparison.py
mock_alchemy/mocking.py
mock_alchemy/unittests.py
mock_alchemy/utils.py
mock_alchemy-0.2.6.dist-info/LICENSE.rst
mock_alchemy-0.2.6.dist-info/METADATA
mock_alchemy-0.2.6.dist-info/WHEEL
mock_alchemy-0.2.6.dist-info/RECORD
