Metadata-Version: 2.1
Name: mock-alchemy
Version: 0.2.6
Summary: SQLAlchemy mock helpers.
Home-page: https://github.com/rajivsarvepalli/mock-alchemy
License: MIT
Keywords: sqlalchemy mock testing,sqlalchemy mock,mock sqlalchemy
Author: Rajiv Sarvepalli
Author-email: rajiv@sarvepalli.net
Requires-Python: >=3.7,<4.0
Classifier: Development Status :: 2 - Pre-Alpha
Classifier: Intended Audience :: Developers
Classifier: License :: OSI Approved :: MIT License
Classifier: Natural Language :: English
Classifier: Programming Language :: Python
Classifier: Programming Language :: Python :: 3
Classifier: Programming Language :: Python :: 3.7
Classifier: Programming Language :: Python :: 3.8
Classifier: Programming Language :: Python :: 3.9
Classifier: Programming Language :: Python :: 3.10
Classifier: Programming Language :: Python :: 3.11
Classifier: Programming Language :: Python :: 3
Classifier: Programming Language :: Python :: 3.10
Classifier: Programming Language :: Python :: 3.11
Classifier: Programming Language :: Python :: 3.7
Classifier: Programming Language :: Python :: 3.8
Classifier: Programming Language :: Python :: 3.9
Requires-Dist: SQLAlchemy (>=2.0.6,<3.0.0)
Project-URL: Changelog, https://github.com/rajivsarvepalli/mock-alchemy/releases
Project-URL: Documentation, https://mock-alchemy.readthedocs.io
Project-URL: Repository, https://github.com/rajivsarvepalli/mock-alchemy
